{
    "links": {
        "-L4wBX64lVnz_5nhFJY-": {
            "added": 1518207115,
            "media": "book:19161852",
            "music": "track:6wjb6rlWb4P8NRcZpP17UJ",
            "tags": [
                "Syenite",
                " orogenes"
            ],
            "uid": "argfktkjctj5wyte1c3wsqt70"
        },
        "-L4wBv5X5JPBP6bG0j1y": {
            "added": 1518207218,
            "media": "movie:140607",
            "music": "track:3EQBVWHnCv19VW8JSxiNzi",
            "tags": [
                "Rey"
            ],
            "uid": "argfktkjctj5wyte1c3wsqt70"
        },
        "-L4wC29Gbvj0mVoQLbOP": {
            "added": 1518207251,
            "media": "movie:68726",
            "music": "track:5QTxFnGygVM4jFQiBovmRo",
            "tags": [
                "Newt/Hermann"
            ],
            "uid": "argfktkjctj5wyte1c3wsqt70"
        },
        "-L4wC7ZFVRsFRMYJU5Nj": {
            "added": 1518207273,
            "media": "tv:40008",
            "music": "track:3AqPL1n1wKc5DVFFnYuJhp",
            "tags": [
                "Will/Hannibal"
            ],
            "uid": "argfktkjctj5wyte1c3wsqt70"
        },
        "-L4wCH92Be34F50M6vcZ": {
            "added": 1518207312,
            "media": "tv:40008",
            "music": "track:6RYp0F2kV3yYmfn33bcQei",
            "tags": [
                "Will Graham"
            ],
            "uid": "argfktkjctj5wyte1c3wsqt70"
        },
        "-L4wCP8s8qTyEn6RkMTk": {
            "added": 1518207345,
            "media": "tv:40008",
            "music": "track:6b8SesYPikYAD26JnB1Ong",
            "tags": [
                "Abigail Hobbs"
            ],
            "uid": "argfktkjctj5wyte1c3wsqt70"
        },
        "-L4wCVQu9gi8MSrRY-W5": {
            "added": 1518207370,
            "media": "tv:61664",
            "music": "track:316r1KLN0bcmpr7TZcMCXT",
            "uid": "argfktkjctj5wyte1c3wsqt70"
        },
        "-L4wC_RST9KwB_xEUB84": {
            "added": 1518207391,
            "media": "book:375802",
            "music": "track:4G8gkOterJn0Ywt6uhqbhp",
            "tags": [
                "Ender Wiggin"
            ],
            "uid": "argfktkjctj5wyte1c3wsqt70"
        },
        "-L4wCeaiuYqYt8bmBWho": {
            "added": 1518207412,
            "media": "movie:679",
            "music": "track:1nNEIBmw6IXlsCOEssCjLr",
            "tags": [
                "Bishop"
            ],
            "uid": "argfktkjctj5wyte1c3wsqt70"
        },
        "-L4wFUFLFuirpzZHrMGN": {
            "added": 1518208152,
            "media": "movie:1417",
            "music": "track:0KQ1LhU7vGiXqn7eAw1nfl",
            "tags": [
                "Ofelia"
            ],
            "uid": "argfktkjctj5wyte1c3wsqt70"
        },
        "-L4wFeA7ZF-9XeeY5Riq": {
            "added": 1518208197,
            "media": "tv:246",
            "music": "track:6C7ZgThn6Yan5MTZdAEEFw",
            "tags": [
                "Toph"
            ],
            "uid": "argfktkjctj5wyte1c3wsqt70"
        },
        "-L4wFoi4J-6eivID1ZNI": {
            "added": 1518208240,
            "media": "book:6437061",
            "music": "track:11XMjzsyPB5LYOwMb058bT",
            "tags": [
                "Sieh"
            ],
            "uid": "argfktkjctj5wyte1c3wsqt70"
        },
        "-L4wG0fF0om2CIjoZYhH": {
            "added": 1518208293,
            "media": "tv:66732",
            "music": "track:163F4SPkExGwITk7VKz5sp",
            "tags": [
                "Will Byers"
            ],
            "uid": "argfktkjctj5wyte1c3wsqt70"
        },
        "-L4wGDre9vGE7Bk4C0E1": {
            "added": 1518208347,
            "media": "book:17675462",
            "music": "track:5vYACMtTGcNEPRgfwZ06t4",
            "tags": [
                "Cabeswater"
            ],
            "uid": "argfktkjctj5wyte1c3wsqt70"
        },
        "-L4wGNnpfoKm7rYJXv3f": {
            "added": 1518208388,
            "media": "book:17675462",
            "music": "track:0YHLczbj1HPhoYrIToH0VI",
            "tags": [
                "Noah Czerny"
            ],
            "uid": "argfktkjctj5wyte1c3wsqt70"
        }
    },
    "media": {
        "book:17675462": {
            "id": "17675462",
            "image": "https://images.gr-assets.com/books/1477103737l/17675462.jpg",
            "last_cached": 1518208388,
            "small_image": "https://images.gr-assets.com/books/1477103737m/17675462.jpg",
            "subtitle": "Maggie Stiefvater",
            "title": "The Raven Boys (The Raven Cycle, #1)",
            "type": "book"
        },
        "book:19161852": {
            "id": "19161852",
            "image": "https://images.gr-assets.com/books/1386803701l/19161852.jpg",
            "last_cached": 1518207193,
            "small_image": "https://images.gr-assets.com/books/1386803701m/19161852.jpg",
            "subtitle": "N.K. Jemisin",
            "title": "The Fifth Season (The Broken Earth, #1)",
            "type": "book"
        },
        "book:375802": {
            "id": "375802",
            "image": "https://images.gr-assets.com/books/1408303130l/375802.jpg",
            "last_cached": 1518207392,
            "small_image": "https://images.gr-assets.com/books/1408303130m/375802.jpg",
            "subtitle": "Orson Scott Card",
            "title": "Ender's Game (Ender's Saga, #1)",
            "type": "book"
        },
        "book:6437061": {
            "id": "6437061",
            "image": "https://images.gr-assets.com/books/1303143211l/6437061.jpg",
            "last_cached": 1518208241,
            "small_image": "https://images.gr-assets.com/books/1303143211m/6437061.jpg",
            "subtitle": "N.K. Jemisin",
            "title": "The Hundred Thousand Kingdoms (Inheritance Trilogy, #1)",
            "type": "book"
        },
        "movie:140607": {
            "id": 140607,
            "image": "https://image.tmdb.org/t/p/w400_and_h600_bestv2/weUSwMdQIa3NaXVzwUoIIcAi85d.jpg",
            "last_cached": 1518207218,
            "small_image": "http://image.tmdb.org/t/p/w185/weUSwMdQIa3NaXVzwUoIIcAi85d.jpg",
            "subtitle": "2015",
            "title": "Star Wars: The Force Awakens",
            "type": "movie"
        },
        "movie:1417": {
            "id": 1417,
            "image": "https://image.tmdb.org/t/p/w400_and_h600_bestv2/t0TDsqbCTgSi0AL7k4baZrOYYhi.jpg",
            "last_cached": 1518208152,
            "small_image": "http://image.tmdb.org/t/p/w185/t0TDsqbCTgSi0AL7k4baZrOYYhi.jpg",
            "subtitle": "2006",
            "title": "Pan's Labyrinth",
            "type": "movie"
        },
        "movie:679": {
            "id": 679,
            "image": "https://image.tmdb.org/t/p/w400_and_h600_bestv2/nORMXEkYEbzkU5WkMWMgRDJwjSZ.jpg",
            "last_cached": 1518208108,
            "small_image": "http://image.tmdb.org/t/p/w185/nORMXEkYEbzkU5WkMWMgRDJwjSZ.jpg",
            "subtitle": "1986",
            "title": "Aliens",
            "type": "movie"
        },
        "movie:68726": {
            "id": 68726,
            "image": "https://image.tmdb.org/t/p/w400_and_h600_bestv2/sCJEwEShZvruTpQ2a4yiX3Q9EyZ.jpg",
            "last_cached": 1518207251,
            "small_image": "http://image.tmdb.org/t/p/w185/sCJEwEShZvruTpQ2a4yiX3Q9EyZ.jpg",
            "subtitle": "2013",
            "title": "Pacific Rim",
            "type": "movie"
        },
        "tv:246": {
            "id": 246,
            "image": "https://image.tmdb.org/t/p/w400_and_h600_bestv2/sB8V0pQtJZ17v8FLXMOcYz6045c.jpg",
            "last_cached": 1518208197,
            "small_image": "http://image.tmdb.org/t/p/w185/sB8V0pQtJZ17v8FLXMOcYz6045c.jpg",
            "subtitle": "2005",
            "title": "Avatar: The Last Airbender",
            "type": "tv"
        },
        "tv:40008": {
            "id": 40008,
            "image": "https://image.tmdb.org/t/p/w400_and_h600_bestv2/kArcGHvTb7m1v6RFHdU40jpiGZD.jpg",
            "last_cached": 1518207345,
            "small_image": "http://image.tmdb.org/t/p/w185/kArcGHvTb7m1v6RFHdU40jpiGZD.jpg",
            "subtitle": "2013",
            "title": "Hannibal",
            "type": "tv"
        },
        "tv:61664": {
            "id": 61664,
            "image": "https://image.tmdb.org/t/p/w400_and_h600_bestv2/kmyvlQ9QKzgdZY31rXaUlgCnzrB.jpg",
            "last_cached": 1518207371,
            "small_image": "http://image.tmdb.org/t/p/w185/kmyvlQ9QKzgdZY31rXaUlgCnzrB.jpg",
            "subtitle": "2015",
            "title": "Sense8",
            "type": "tv"
        },
        "tv:66732": {
            "id": 66732,
            "image": "https://image.tmdb.org/t/p/w400_and_h600_bestv2/lXS60geme1LlEob5Wgvj3KilClA.jpg",
            "last_cached": 1518208293,
            "small_image": "http://image.tmdb.org/t/p/w185/lXS60geme1LlEob5Wgvj3KilClA.jpg",
            "subtitle": "2016",
            "title": "Stranger Things",
            "type": "tv"
        }
    },
    "tracks": {
        "0KQ1LhU7vGiXqn7eAw1nfl": {
            "id": "0KQ1LhU7vGiXqn7eAw1nfl",
            "image": "https://i.scdn.co/image/4f3a6e2aebbbba0540fbe556e03a2a023c67a7cc",
            "last_cached": 1518208152,
            "small_image": "https://i.scdn.co/image/46d6e9962f510ab123b6034e335102419d4388d4",
            "subtitle": "Meg & Dia",
            "title": "Monster"
        },
        "0YHLczbj1HPhoYrIToH0VI": {
            "id": "0YHLczbj1HPhoYrIToH0VI",
            "image": "https://i.scdn.co/image/39d9e25c75af01dfcf73d7c66aaeca968ef827f4",
            "last_cached": 1518208388,
            "small_image": "https://i.scdn.co/image/2cc0420f6b778b411e4ebb9c31d4546f31e84c7e",
            "subtitle": "Truslow",
            "title": "Dead"
        },
        "11XMjzsyPB5LYOwMb058bT": {
            "id": "11XMjzsyPB5LYOwMb058bT",
            "image": "https://i.scdn.co/image/bc1f29480b1250624ebe7ca17963cc370f7793b5",
            "last_cached": 1518208240,
            "small_image": "https://i.scdn.co/image/62b4ba7a26b31c7f5bc487bc07cc4d6708f87e31",
            "subtitle": "Imogen Heap",
            "title": "Little Bird"
        },
        "163F4SPkExGwITk7VKz5sp": {
            "id": "163F4SPkExGwITk7VKz5sp",
            "image": "https://i.scdn.co/image/2cf1b79f2663619a87a2732dfb3cba153a9707e1",
            "last_cached": 1518208293,
            "small_image": "https://i.scdn.co/image/2ed6f4a26d7e6ec311901d8694ed18b4097d3866",
            "subtitle": "Bad Suns",
            "title": "Salt"
        },
        "1nNEIBmw6IXlsCOEssCjLr": {
            "id": "1nNEIBmw6IXlsCOEssCjLr",
            "image": "https://i.scdn.co/image/1cd75171d6593fc4d9b59fdcfeb2d0577d660649",
            "last_cached": 1518207412,
            "small_image": "https://i.scdn.co/image/fef855276d708f81597545359d1697c538dd4a05",
            "subtitle": "Fall Out Boy",
            "title": "Bishops Knife Trick"
        },
        "316r1KLN0bcmpr7TZcMCXT": {
            "id": "316r1KLN0bcmpr7TZcMCXT",
            "image": "https://i.scdn.co/image/a2aba574af86865eee08624042b1bf75d15cc362",
            "last_cached": 1518207370,
            "small_image": "https://i.scdn.co/image/a5a8d74562e8df93438e8942599cd1538c92a9b6",
            "subtitle": "The 1975",
            "title": "The Sound"
        },
        "3AqPL1n1wKc5DVFFnYuJhp": {
            "id": "3AqPL1n1wKc5DVFFnYuJhp",
            "image": "https://i.scdn.co/image/5ecc248cd9fa66657f5444b07e01afb9c39788c7",
            "last_cached": 1518207273,
            "small_image": "https://i.scdn.co/image/cadb21920d477864a5bacf701dcc03d5d035567e",
            "subtitle": "The Cinematic Orchestra",
            "title": "To Build A Home"
        },
        "3EQBVWHnCv19VW8JSxiNzi": {
            "id": "3EQBVWHnCv19VW8JSxiNzi",
            "image": "https://i.scdn.co/image/59605b524453747b491863e096a370d207467e9a",
            "last_cached": 1518207217,
            "small_image": "https://i.scdn.co/image/ecaa355c3c23bb95488481dc4210e6db3395d77a",
            "subtitle": "Bad Suns",
            "title": "20 Years"
        },
        "4G8gkOterJn0Ywt6uhqbhp": {
            "id": "4G8gkOterJn0Ywt6uhqbhp",
            "image": "https://i.scdn.co/image/443609cd35e43c7bdb272b3d1d9e80290e128bc5",
            "last_cached": 1518207391,
            "small_image": "https://i.scdn.co/image/64e279e82a7d78e1bcb2579bceb54341ef2465b0",
            "subtitle": "Imagine Dragons",
            "title": "Radioactive"
        },
        "5QTxFnGygVM4jFQiBovmRo": {
            "id": "5QTxFnGygVM4jFQiBovmRo",
            "image": "https://i.scdn.co/image/6bd4450a8fbf30702a92f1c825377f1933ded249",
            "last_cached": 1518207250,
            "small_image": "https://i.scdn.co/image/587d47747f51b575a75684e64e8da0c5b1432fb5",
            "subtitle": "Blue Öyster Cult",
            "title": "(Don't Fear) The Reaper"
        },
        "5vYACMtTGcNEPRgfwZ06t4": {
            "id": "5vYACMtTGcNEPRgfwZ06t4",
            "image": "https://i.scdn.co/image/69bb8bc83ba8645fff2dfa00fd7434866994e5a9",
            "last_cached": 1518208347,
            "small_image": "https://i.scdn.co/image/07807f2691744fe60309720cf38282fa20082a81",
            "subtitle": "Rags & Ribbons",
            "title": "Gymnopedie 5"
        },
        "6C7ZgThn6Yan5MTZdAEEFw": {
            "id": "6C7ZgThn6Yan5MTZdAEEFw",
            "image": "https://i.scdn.co/image/43d0690cdcb496979a3516501afb823ce451a1cd",
            "last_cached": 1518208197,
            "small_image": "https://i.scdn.co/image/faeb5b03abf31cc1523913ce7356b66eecfbe72b",
            "subtitle": "LL Cool J",
            "title": "Mama Said Knock You Out"
        },
        "6RYp0F2kV3yYmfn33bcQei": {
            "id": "6RYp0F2kV3yYmfn33bcQei",
            "image": "https://i.scdn.co/image/c68239fcca96faf85867b14d35f345ebe2b0a210",
            "last_cached": 1518207312,
            "small_image": "https://i.scdn.co/image/2aafe1a07ff15ba82840d9da404c9bb64faf0296",
            "subtitle": "Everything Everything",
            "title": "Regret"
        },
        "6b8SesYPikYAD26JnB1Ong": {
            "id": "6b8SesYPikYAD26JnB1Ong",
            "image": "https://i.scdn.co/image/346014a6f618366de08e2555764a9bec0e59339a",
            "last_cached": 1518207345,
            "small_image": "https://i.scdn.co/image/ffcb4ddb07618eaf25b198693ff28faca011fe7b",
            "subtitle": "Jukebox The Ghost",
            "title": "Miss Templeton's 7000th Dream"
        },
        "6wjb6rlWb4P8NRcZpP17UJ": {
            "id": "6wjb6rlWb4P8NRcZpP17UJ",
            "image": "https://i.scdn.co/image/791353302b5393cc3e6e903beb02c85f47b43a66",
            "last_cached": 1518207195,
            "small_image": "https://i.scdn.co/image/1625eaa94bc5a0289a14168e2340656b2e178663",
            "subtitle": "Bad Suns",
            "title": "Maybe We're Meant To Be Alone"
        }
    },
    "users": {
        "argfktkjctj5wyte1c3wsqt70": {
            "display_name": "Kenzie",
            "external_urls": {
                "spotify": "https://open.spotify.com/user/argfktkjctj5wyte1c3wsqt70"
            },
            "followers": {
                "total": 31
            },
            "href": "https://api.spotify.com/v1/users/argfktkjctj5wyte1c3wsqt70",
            "id": "argfktkjctj5wyte1c3wsqt70",
            "images": [
                {
                    "url": "https://profile-images.scdn.co/images/userprofile/default/e4f86e02ceee0bd7c9fda9fec7effa3a71693756"
                }
            ],
            "type": "user",
            "uri": "spotify:user:argfktkjctj5wyte1c3wsqt70",
            "username": "argfktkjctj5wyte1c3wsqt70"
        }
    }
}